<?xml version="1.0" encoding="UTF-8" standalone="no"?><feature id="org.openscada.da" label="openSCADA DA" provider-name="openSCADA.org" version="1.1.0.v20130529">

   <description>
      openSCADA DA Feature
   </description>

   <copyright>
      %copyright
   </copyright>

   <license url="http://opensource.org/licenses/lgpl-3.0.html">
      %license
   </license>

   <requires>
      <import feature="org.openscada.aurora" version="1.1.0.qualifier"/>
      <import feature="org.openscada.external" version="1.1.0.qualifier"/>
   </requires>

   <plugin download-size="0" id="org.openscada.da.client" install-size="0" unpack="false" version="0.0.0"/>

   <plugin download-size="0" id="org.openscada.da.client.net" install-size="0" unpack="false" version="0.0.0"/>

   <plugin download-size="0" id="org.openscada.da.core.common" install-size="0" unpack="false" version="0.0.0"/>

   <plugin download-size="0" id="org.openscada.da.core.server" install-size="0" unpack="false" version="0.0.0"/>

   <plugin download-size="0" id="org.openscada.da.net" install-size="0" unpack="false" version="0.0.0"/>

   <plugin download-size="0" id="org.openscada.da.server.common" install-size="0" unpack="false" version="0.0.0"/>

   <plugin download-size="0" id="org.openscada.da.server.exec" install-size="0" unpack="false" version="0.0.0"/>

   <plugin download-size="0" id="org.openscada.da.server.exporter" install-size="0" unpack="false" version="0.0.0"/>

   <plugin download-size="0" id="org.openscada.da.server.jdbc" install-size="0" unpack="false" version="0.0.0"/>

   <plugin download-size="0" id="org.openscada.da.server.net" install-size="0" unpack="false" version="0.0.0"/>

   <plugin download-size="0" id="org.openscada.da.server.opc" install-size="0" unpack="false" version="0.0.0"/>

   <plugin download-size="0" id="org.openscada.da.server.proxy" install-size="0" unpack="false" version="0.0.0"/>

   <plugin download-size="0" id="org.openscada.da.server.simulation.component" install-size="0" unpack="false" version="0.0.0"/>

   <plugin download-size="0" id="org.openscada.da.server.snmp" install-size="0" unpack="false" version="0.0.0"/>

   <plugin download-size="0" id="org.openscada.da.server.stock" install-size="0" unpack="false" version="0.0.0"/>

   <plugin download-size="0" id="org.openscada.da.server.sysinfo" install-size="0" unpack="false" version="0.0.0"/>

   <plugin download-size="0" id="org.openscada.da.server.test" install-size="0" unpack="false" version="0.0.0"/>

   <plugin download-size="0" id="org.openscada.da.client.connection.service" install-size="0" unpack="false" version="0.0.0"/>

   <plugin download-size="0" id="org.openscada.da.connection.provider" install-size="0" unpack="false" version="0.0.0"/>

   <plugin download-size="0" id="org.openscada.da.master" install-size="0" unpack="false" version="0.0.0"/>

   <plugin download-size="0" id="org.openscada.da.server.osgi" install-size="0" unpack="false" version="0.0.0"/>

   <plugin download-size="0" id="org.openscada.da.server.osgi.exporter.net" install-size="0" unpack="false" version="0.0.0"/>

   <plugin download-size="0" id="org.openscada.da.server.osgi.testing" install-size="0" unpack="false" version="0.0.0"/>

   <plugin download-size="0" id="org.openscada.da.datasource" install-size="0" unpack="false" version="0.0.0"/>

   <plugin download-size="0" id="org.openscada.da.datasource.item" install-size="0" unpack="false" version="0.0.0"/>

   <plugin download-size="0" id="org.openscada.da.datasource.proxy" install-size="0" unpack="false" version="0.0.0"/>

   <plugin download-size="0" id="org.openscada.da.master.common" install-size="0" unpack="false" version="0.0.0"/>

   <plugin download-size="0" id="org.openscada.da.server.dave" install-size="0" unpack="false" version="0.0.0"/>

   <plugin download-size="0" id="org.openscada.da.datasource.script" install-size="0" unpack="false" version="0.0.0"/>

   <plugin download-size="0" id="org.openscada.da.server.common.osgi" install-size="0" unpack="false" version="0.0.0"/>

   <plugin download-size="0" id="org.openscada.da.master.analyzer" install-size="0" unpack="false" version="0.0.0"/>

   <plugin download-size="0" id="org.openscada.da.datasource.average" install-size="0" unpack="false" version="0.0.0"/>

   <plugin download-size="0" id="org.openscada.da.datasource.movingaverage" install-size="0" unpack="false" version="0.0.0"/>

   <plugin download-size="0" id="org.openscada.da.datasource.memory" install-size="0" unpack="false" version="0.0.0"/>

   <plugin download-size="0" id="org.openscada.da.datasource.sum" install-size="0" unpack="false" version="0.0.0"/>

   <plugin download-size="0" id="org.openscada.da.datasource.ds" install-size="0" unpack="false" version="0.0.0"/>

   <plugin download-size="0" id="org.openscada.da.server.osgi.summary" install-size="0" unpack="false" version="0.0.0"/>

   <plugin download-size="0" id="org.openscada.da.datasource.formula" install-size="0" unpack="false" version="0.0.0"/>

   <plugin download-size="0" id="org.openscada.da.server.arduino" install-size="0" unpack="false" version="0.0.0"/>

   <plugin download-size="0" id="org.openscada.da.component.script" install-size="0" version="0.0.0"/>

   <plugin download-size="0" id="org.openscada.da.utils.daemon" install-size="0" unpack="false" version="0.0.0"/>

   <plugin download-size="0" id="org.openscada.da.mapper" install-size="0" unpack="false" version="0.0.0"/>

   <plugin download-size="0" id="org.openscada.da.master.mapper" install-size="0" unpack="false" version="0.0.0"/>

   <plugin download-size="0" id="org.openscada.da.mapper.osgi" install-size="0" version="0.0.0"/>

   <plugin download-size="0" id="org.openscada.da.datasource.constant" install-size="0" unpack="false" version="0.0.0"/>

   <plugin download-size="0" id="org.openscada.da.common.ngp" install-size="0" unpack="false" version="0.0.0"/>

   <plugin download-size="0" id="org.openscada.da.server.ngp" install-size="0" unpack="false" version="0.0.0"/>

   <plugin download-size="0" id="org.openscada.da.client.ngp" install-size="0" unpack="false" version="0.0.0"/>

   <plugin download-size="0" id="org.openscada.da.server.exporter.ngp" install-size="0" unpack="false" version="0.0.0"/>

   <plugin download-size="0" id="org.openscada.da.server.modbus" install-size="0" unpack="false" version="0.0.0"/>

</feature>